fbi_wanted/__init__.py
fbi_wanted/fbi_wanted.py
fbi_wanted-0.1.0.dist-info/LICENSE
fbi_wanted-0.1.0.dist-info/METADATA
fbi_wanted-0.1.0.dist-info/WHEEL
fbi_wanted-0.1.0.dist-info/top_level.txt
fbi_wanted-0.1.0.dist-info/RECORD
