Metadata-Version: 2.1
Name: fbi-wanted
Version: 0.1.0
Summary: A library for accessing the FBI Wanted API.
Home-page: https://github.com/ininike/fbi-wanted-search
Author: Inioluwa Adenaike
Author-email: Inioluwa Adenaike <inioluwadenaike@gmail.com>
License: MIT
Keywords: FBI,wanted,API,OSINT
Classifier: Programming Language :: Python :: 3
Classifier: License :: OSI Approved :: MIT License
Classifier: Operating System :: OS Independent
Requires-Python: >=3.6
License-File: LICENSE
Requires-Dist: requests>=2.25.1
Requires-Dist: asyncio>=3.4.3
